strx/__init__.py
strx/_constant.py
strx/convert.py
strx/normalize.py
strx/transform.py
strx-0.3.1.dist-info/METADATA
strx-0.3.1.dist-info/WHEEL
strx-0.3.1.dist-info/licenses/LICENSE
strx-0.3.1.dist-info/RECORD
