Metadata-Version: 2.4
Name: strx
Version: 0.3.1
Summary: Consistent API for string workloads
Project-URL: Documentation, https://github.com/thuyetbao/strx#README
Project-URL: Issues, https://github.com/thuyetbao/strx/issues
Project-URL: Source, https://github.com/thuyetbao/strx
Author-email: Thuyet Bao <trthuyetbao@gmail.com>
License-Expression: MIT
License-File: LICENSE
Keywords: python3,strx
Classifier: Development Status :: 5 - Production/Stable
Classifier: Operating System :: OS Independent
Classifier: Programming Language :: Python
Classifier: Programming Language :: Python :: 3
Classifier: Programming Language :: Python :: 3.12
Classifier: Programming Language :: Python :: 3.13
Requires-Python: >=3.12
